CHANGES.rst
MANIFEST.in
setup.py
Products/__init__.py
Products.PloneHotfix20161129.egg-info/PKG-INFO
Products.PloneHotfix20161129.egg-info/SOURCES.txt
Products.PloneHotfix20161129.egg-info/dependency_links.txt
Products.PloneHotfix20161129.egg-info/entry_points.txt
Products.PloneHotfix20161129.egg-info/namespace_packages.txt
Products.PloneHotfix20161129.egg-info/not-zip-safe
Products.PloneHotfix20161129.egg-info/requires.txt
Products.PloneHotfix20161129.egg-info/top_level.txt
Products/PloneHotfix20161129/README.txt
Products/PloneHotfix20161129/__init__.py
Products/PloneHotfix20161129/apply.pt
Products/PloneHotfix20161129/comments.py
Products/PloneHotfix20161129/configure.zcml
Products/PloneHotfix20161129/copy.py
Products/PloneHotfix20161129/publishing.py
docs/LICENSE.GPL
docs/LICENSE.txt