Metadata-Version: 1.1
Name: Products.PloneHotfix20161129
Version: 1.1
Summary: Various Plone hotfixes, 2016-11-29
Home-page: https://github.com/plone
Author: Plone Security Team
Author-email: security@plone.org
License: GPL
Keywords: plone security hotfix patch
Platform: UNKNOWN
Classifier: Framework :: Plone
Classifier: Programming Language :: Python
